cihai/__about__.py
cihai/__init__.py
cihai/config.py
cihai/constants.py
cihai/conversion.py
cihai/core.py
cihai/db.py
cihai/exc.py
cihai/extend.py
cihai/log.py
cihai/types.py
cihai/utils.py
cihai/_internal/__init__.py
cihai/_internal/config_reader.py
cihai/_internal/types.py
cihai/data/__init__.py
cihai/data/decomp/__init__.py
cihai/data/unihan/__init__.py
cihai/data/unihan/bootstrap.py
cihai/data/unihan/constants.py
cihai/data/unihan/dataset.py
cihai-0.36.1.dist-info/METADATA
cihai-0.36.1.dist-info/WHEEL
cihai-0.36.1.dist-info/licenses/LICENSE
cihai-0.36.1.dist-info/RECORD
