Metadata-Version: 2.4
Name: cihai
Version: 0.36.1
Summary: Library for CJK (chinese, japanese, korean) language data.
Project-URL: Bug Tracker, https://github.com/cihai/cihai/issues
Project-URL: Documentation, https://cihai.git-pull.com
Project-URL: Repository, https://github.com/cihai/cihai
Project-URL: Release notes, https://github.com/cihai/cihai/blob/master/CHANGES
Project-URL: Q & A, https://github.com/cihai/cihai/discussions
Author-email: Tony Narlock <tony@git-pull.com>
License: MIT
License-File: LICENSE
Keywords: chinese,cjk,dataset,dictionary,encyclopedia,japanese,korean,languages,library,sqlalchemy,study,unicode,unihan
Classifier: Development Status :: 4 - Beta
Classifier: Environment :: Web Environment
Classifier: Intended Audience :: Developers
Classifier: License :: OSI Approved :: MIT License
Classifier: Programming Language :: Python
Classifier: Programming Language :: Python :: 3
Classifier: Programming Language :: Python :: 3.10
Classifier: Programming Language :: Python :: 3.11
Classifier: Programming Language :: Python :: 3.12
Classifier: Programming Language :: Python :: 3.13
Classifier: Programming Language :: Python :: 3.14
Classifier: Programming Language :: Python :: Implementation :: PyPy
Classifier: Topic :: Software Development :: Internationalization
Classifier: Topic :: Software Development :: Localization
Classifier: Topic :: Utilities
Requires-Python: <4.0,>=3.10
Requires-Dist: appdirs
Requires-Dist: pyyaml~=6.0
Requires-Dist: sqlalchemy[mypy]~=2.0
Requires-Dist: unihan-etl~=0.39.1
